README.md
setup.py
pj_rf_testrail/__init__.py
pj_rf_testrail/pj_rf_testrail.py
pj_rf_testrail.egg-info/PKG-INFO
pj_rf_testrail.egg-info/SOURCES.txt
pj_rf_testrail.egg-info/dependency_links.txt
pj_rf_testrail.egg-info/top_level.txt